{
  "metadata": {
    "pedigreeName": "Chefadora",
    "rootHorseId": "chefadora",
    "lastUpdated": "2025-10-04T17:35:00.000Z",
    "source": "attribute_mapping_reverted"
  },
  "horses": [
    {
      "id": "chefadora",
      "name": "シエフアドラ",
      "foaled": {
        "year": 1968
      },
      "sex": "female",
      "breed": "サラブレッド種",
      "sire": "Chieftain",
      "dam": "Isadora",
      "color": "鹿毛",
      "breeder": "米",
      "netkeibaId": "000a00057b",
      "raceStats": {
        "total": {
          "runs": 0,
          "wins": 0
        },
        "divisions": []
      },
      "raceResults": [],
      "source": "python_scraping",
      "englishName": "Chefadora"
    },
    {
      "id": "kachiumataroo",
      "name": "カチウマタロー",
      "foaled": {
        "year": 1975,
        "month": 5,
        "day": 14
      },
      "sex": "male",
      "breed": "サラブレッド種",
      "sire": "ヒッティングアウェー(US)",
      "dam": "シエフアドラ",
      "color": "鹿毛",
      "breeder": "ダービースタッド（幕別町）",
      "netkeibaId": "1975z00974",
      "raceStats": {
        "total": {
          "runs": 33,
          "wins": 5
        },
        "divisions": []
      },
      "raceResults": [
        {
          "date": {
            "year": 1981,
            "month": 4,
            "day": 5
          },
          "racecourse": "中山",
          "race": "中山大障害(OP)",
          "displayRace": "中山大障害(春)",
          "distance": "障4100",
          "grade": "jra_grandjump",
          "entry": "10",
          "result": "6",
          "favorite": "6"
        },
        {
          "date": {
            "year": 1981,
            "month": 1,
            "day": 31
          },
          "racecourse": "東京",
          "race": "東京障害特別(OP)",
          "displayRace": "東京障害特別(春)",
          "distance": "障3300",
          "grade": "jra_jump",
          "entry": "7",
          "result": "7",
          "favorite": "5"
        },
        {
          "date": {
            "year": 1980,
            "month": 12,
            "day": 20
          },
          "racecourse": "中山",
          "race": "中山大障害(OP)",
          "displayRace": "中山大障害(秋)",
          "distance": "障4100",
          "grade": "jra_grandjump",
          "entry": "10",
          "result": "1",
          "favorite": "8"
        },
        {
          "date": {
            "year": 1980,
            "month": 11,
            "day": 9
          },
          "racecourse": "東京",
          "race": "東京障害特別(OP)",
          "displayRace": "東京障害特別(秋)",
          "distance": "障3300",
          "grade": "jra_jump",
          "entry": "7",
          "result": "4",
          "favorite": "6"
        },
        {
          "date": {
            "year": 1980,
            "month": 4,
            "day": 6
          },
          "racecourse": "中山",
          "race": "中山大障害(OP)",
          "displayRace": "中山大障害(春)",
          "distance": "障4100",
          "grade": "jra_grandjump",
          "entry": "5",
          "result": "3",
          "favorite": "4"
        },
        {
          "date": {
            "year": 1979,
            "month": 12,
            "day": 23
          },
          "racecourse": "中山",
          "race": "中山大障害(OP)",
          "displayRace": "中山大障害(秋)",
          "distance": "障4100",
          "grade": "jra_grandjump",
          "entry": "7",
          "result": "6",
          "favorite": "7"
        },
        {
          "date": {
            "year": 1979,
            "month": 6,
            "day": 3
          },
          "racecourse": "東京",
          "race": "東京障害特別(OP)",
          "displayRace": "東京障害特別(春)",
          "distance": "障3300",
          "grade": "jra_jump",
          "entry": "10",
          "result": "3",
          "favorite": "5"
        }
      ],
      "source": "python_scraping",
      "prizeMoney": {
        "total": "0万円"
      },
      "damId": "chefadora"
    }
  ]
}
