{
  "metadata": {
    "pedigreeName": "アントルソール",
    "rootHorseId": "entresol",
    "lastUpdated": "2025-09-07T14:36:11.068Z",
    "source": "tsx_conversion_babel"
  },
  "horses": [
    {
      "id": "entresol",
      "name": "アントルソール",
      "foaled": "1910",
      "foaledArray": ["1910"],
      "sex": "female",
      "breed": "サラブレッド種",
      "sire": "",
      "dam": "",
      "color": "",
      "breeder": "",
      "netkeibaId": "000a0180d9",
      "source": "tsx_conversion",
      "owner": "日高種馬牧場"
    }
  ]
}
