{
  "metadata": {
    "pedigreeName": "Exodus",
    "rootHorseId": "exodus",
    "lastUpdated": "2025-09-20T16:56:02.358636Z",
    "source": "python_scraping"
  },
  "horses": [
    {
      "id": "exodus",
      "name": "Exodus",
      "foaled": "{'year': 1999}",
      "foaledArray": ["1999"],
      "sex": "female",
      "breed": "サラブレッド種",
      "sire": "Kaapstad",
      "dam": "Lady Genesis",
      "color": "鹿毛",
      "breeder": "",
      "netkeibaId": "000a01296d",
      "raceStats": {
        "total": {
          "runs": 0,
          "wins": 0
        },
        "divisions": []
      },
      "raceResults": [],
      "source": "python_scraping"
    },
    {
      "id": "aerovelocity",
      "name": "エアロヴェロシティ",
      "foaled": "{'year': 2008, 'month': 9, 'day': 8}",
      "foaledArray": ["2008", "09", "08"],
      "sex": "gelding",
      "breed": "サラブレッド種",
      "sire": "Pins",
      "dam": "Exodus",
      "color": "鹿毛",
      "breeder": "N E Schick & S J Till（新）",
      "netkeibaId": "2008190007",
      "raceStats": {
        "total": {
          "runs": 25,
          "wins": 12
        },
        "divisions": []
      },
      "raceResults": [
        {
          "date": {
            "year": 2017,
            "month": 1,
            "day": 30
          },
          "racecourse": "シャティン",
          "race": "センテナリースプリン(GII)",
          "displayRace": "センテナリースプリン〔シャティン〕",
          "distance": "芝1200",
          "grade": "abroad_g2",
          "entry": "8",
          "result": "8",
          "favorite": "3"
        },
        {
          "date": {
            "year": 2016,
            "month": 12,
            "day": 11
          },
          "racecourse": "シャティン",
          "race": "香港スプリント(GI)",
          "displayRace": "香港スプリント〔シャティン〕",
          "distance": "芝1200",
          "grade": "abroad_g1",
          "entry": "14",
          "result": "1",
          "favorite": "4"
        },
        {
          "date": {
            "year": 2016,
            "month": 11,
            "day": 20
          },
          "racecourse": "香港",
          "race": "ジョッキークラブスプ(GII)",
          "displayRace": "ジョッキークラブスプ〔香港〕",
          "distance": "芝1200",
          "grade": "abroad_g2",
          "entry": "10",
          "result": "3",
          "favorite": "3"
        },
        {
          "date": {
            "year": 2016,
            "month": 10,
            "day": 23
          },
          "racecourse": "香港",
          "race": "プレミアボウル(GII)",
          "displayRace": "プレミアボウル〔香港〕",
          "distance": "芝1200",
          "grade": "abroad_g2",
          "entry": "12",
          "result": "3",
          "favorite": "4"
        },
        {
          "date": {
            "year": 2016,
            "month": 5,
            "day": 1
          },
          "racecourse": "香港",
          "race": "チェアマンズスプリン(GI)",
          "displayRace": "チェアマンズスプリン〔香港〕",
          "distance": "芝1200",
          "grade": "abroad_g1",
          "entry": "14",
          "result": "8",
          "favorite": "5"
        },
        {
          "date": {
            "year": 2016,
            "month": 1,
            "day": 31
          },
          "racecourse": "香港",
          "race": "センテナリースプリン(GI)",
          "displayRace": "センテナリースプリン〔香港〕",
          "distance": "芝1200",
          "grade": "abroad_g1",
          "entry": "12",
          "result": "1",
          "favorite": "3"
        },
        {
          "date": {
            "year": 2015,
            "month": 10,
            "day": 25
          },
          "racecourse": "香港",
          "race": "プレミアボウル(GII)",
          "displayRace": "プレミアボウル〔香港〕",
          "distance": "芝1200",
          "grade": "abroad_g2",
          "entry": "14",
          "result": "14",
          "favorite": "1"
        },
        {
          "date": {
            "year": 2015,
            "month": 5,
            "day": 17
          },
          "racecourse": "シンガポール",
          "race": "クリスフライヤーイン(GI)",
          "displayRace": "クリスフライヤーイン〔シンガポール〕",
          "distance": "芝1200",
          "grade": "abroad_g1",
          "entry": "9",
          "result": "1",
          "favorite": "1"
        },
        {
          "date": {
            "year": 2015,
            "month": 3,
            "day": 29
          },
          "racecourse": "中京",
          "race": "高松宮記念(GI)",
          "displayRace": "高松宮記念",
          "distance": "芝1200",
          "grade": "jra_g1",
          "entry": "18",
          "result": "1",
          "favorite": "4"
        },
        {
          "date": {
            "year": 2015,
            "month": 2,
            "day": 15
          },
          "racecourse": "香港",
          "race": "チェアマンズスプリン(GI)",
          "displayRace": "チェアマンズスプリン〔香港〕",
          "distance": "芝1200",
          "grade": "abroad_g1",
          "entry": "12",
          "result": "2",
          "favorite": "1"
        },
        {
          "date": {
            "year": 2014,
            "month": 12,
            "day": 14
          },
          "racecourse": "香港",
          "race": "香港スプリント(GI)",
          "displayRace": "香港スプリント〔香港〕",
          "distance": "芝1200",
          "grade": "abroad_g1",
          "entry": "14",
          "result": "1",
          "favorite": "2"
        },
        {
          "date": {
            "year": 2014,
            "month": 11,
            "day": 23
          },
          "racecourse": "香港",
          "race": "ジョッキークラブスプ(GII)",
          "displayRace": "ジョッキークラブスプ〔香港〕",
          "distance": "芝1200",
          "grade": "abroad_g2",
          "entry": "",
          "result": "14",
          "favorite": "1"
        },
        {
          "date": {
            "year": 2014,
            "month": 10,
            "day": 26
          },
          "racecourse": "香港",
          "race": "プレミアボウル(GII)",
          "displayRace": "プレミアボウル〔香港〕",
          "distance": "芝1200",
          "grade": "abroad_g2",
          "entry": "",
          "result": "1",
          "favorite": "1"
        },
        {
          "date": {
            "year": 2014,
            "month": 6,
            "day": 8
          },
          "racecourse": "香港",
          "race": "プリンスジュエリー&(GIII)",
          "displayRace": "プリンスジュエリー&〔香港〕",
          "distance": "芝1400",
          "grade": "abroad_g3",
          "entry": "",
          "result": "2",
          "favorite": "1"
        },
        {
          "date": {
            "year": 2014,
            "month": 5,
            "day": 25
          },
          "racecourse": "香港",
          "race": "シャティンヴァーズ(GIII)",
          "displayRace": "シャティンヴァーズ〔香港〕",
          "distance": "芝1200",
          "grade": "abroad_g3",
          "entry": "",
          "result": "1",
          "favorite": "3"
        }
      ],
      "source": "python_scraping",
      "englishName": "Aerovelocity",
      "prizeMoney": {
        "total": "9,878万円",
        "central": "9,878万円",
        "local": "0万円"
      },
      "damId": "exodus"
    }
  ]
}
