{
  "metadata": {
    "pedigreeName": "Flaming Fire",
    "rootHorseId": "flaming-fire",
    "lastUpdated": "2025-10-04T17:35:00.000Z",
    "source": "attribute_mapping_reverted"
  },
  "horses": [
    {
      "id": "flaming-fire",
      "name": "フレーミングフアイア",
      "foaled": {
        "year": 1946
      },
      "sex": "female",
      "breed": "サラ",
      "sire": "Signal Light",
      "dam": "Tolerate",
      "color": "栗毛",
      "breeder": "愛",
      "netkeibaId": "000a0028bb",
      "raceStats": {
        "total": {
          "runs": 0,
          "wins": 0
        },
        "divisions": []
      },
      "raceResults": [],
      "source": "python_scraping",
      "englishName": "Flaming Fire"
    },
    {
      "id": "crack-ryu",
      "name": "クラツクリュウ",
      "foaled": {
        "year": 1958
      },
      "sex": "female",
      "breed": "サラ",
      "sire": "ヒンドスタン",
      "dam": "フレーミングフアイア",
      "color": "鹿毛",
      "breeder": "浦河町",
      "netkeibaId": "000a0031cf",
      "raceStats": {
        "total": {
          "runs": 34,
          "wins": 10
        },
        "divisions": []
      },
      "raceResults": [],
      "source": "python_scraping",
      "englishName": "Crack Ryu",
      "prizeMoney": {
        "total": "0万円"
      },
      "damId": "flaming-fire"
    },
    {
      "id": "good-sapphire",
      "name": "グツドサファイア",
      "foaled": {
        "year": 1971
      },
      "sex": "female",
      "breed": "サラ",
      "sire": "ロムルス",
      "dam": "クラツクリュウ",
      "color": "鹿毛",
      "breeder": "静内町",
      "netkeibaId": "000a00512d",
      "raceStats": {
        "total": {
          "runs": 0,
          "wins": 0
        },
        "divisions": []
      },
      "raceResults": [],
      "source": "python_scraping",
      "englishName": "Good Sapphire",
      "prizeMoney": {
        "total": "0万円"
      },
      "damId": "crack-ryu"
    },
    {
      "id": "lovely-star",
      "name": "ラブリースター",
      "foaled": {
        "year": 1979,
        "month": 5,
        "day": 3
      },
      "sex": "female",
      "breed": "サラ",
      "sire": "トウショウボーイ",
      "dam": "グツドサファイア",
      "color": "鹿毛",
      "breeder": "信岡牧場（浦河町）",
      "netkeibaId": "1979104149",
      "raceStats": {
        "total": {
          "runs": 31,
          "wins": 6
        },
        "divisions": []
      },
      "raceResults": [
        {
          "date": {
            "year": 1984,
            "month": 11,
            "day": 18
          },
          "racecourse": "京都",
          "race": "マイルチャンピオンシ(GI)",
          "displayRace": "マイルチャンピングシップ",
          "distance": "芝1600",
          "grade": "jra_g1",
          "entry": "16",
          "result": "12",
          "favorite": "13"
        },
        {
          "date": {
            "year": 1983,
            "month": 12,
            "day": 4
          },
          "racecourse": "中京",
          "race": "農林水産省賞典愛知杯(OP)",
          "displayRace": "愛知杯",
          "distance": "芝2000",
          "grade": "jra_grade",
          "entry": "14",
          "result": "11",
          "favorite": "9"
        },
        {
          "date": {
            "year": 1983,
            "month": 8,
            "day": 28
          },
          "racecourse": "小倉",
          "race": "小倉記念(OP)",
          "displayRace": "小倉記念",
          "distance": "芝2000",
          "grade": "jra_grade",
          "entry": "13",
          "result": "8",
          "favorite": "3"
        },
        {
          "date": {
            "year": 1983,
            "month": 8,
            "day": 7
          },
          "racecourse": "小倉",
          "race": "テレビ西日本賞北九州(OP)",
          "displayRace": "北九州記念",
          "distance": "芝1800",
          "grade": "jra_grade",
          "entry": "10",
          "result": "1",
          "favorite": "1"
        },
        {
          "date": {
            "year": 1983,
            "month": 7,
            "day": 10
          },
          "racecourse": "中京",
          "race": "東海テレビ杯金鯱賞(OP)",
          "displayRace": "金鯱賞",
          "distance": "芝1800",
          "grade": "jra_grade",
          "entry": "20",
          "result": "1",
          "favorite": "10"
        },
        {
          "date": {
            "year": 1983,
            "month": 1,
            "day": 30
          },
          "racecourse": "京都",
          "race": "京都牝馬特別(OP)",
          "displayRace": "京都牝馬特別",
          "distance": "芝1600",
          "grade": "jra_grade",
          "entry": "9",
          "result": "7",
          "favorite": "3"
        },
        {
          "date": {
            "year": 1983,
            "month": 1,
            "day": 23
          },
          "racecourse": "中京",
          "race": "中日新聞杯(OP)",
          "displayRace": "中日新聞杯",
          "distance": "芝1800",
          "grade": "jra_grade",
          "entry": "15",
          "result": "3",
          "favorite": "3"
        },
        {
          "date": {
            "year": 1982,
            "month": 12,
            "day": 19
          },
          "racecourse": "阪神",
          "race": "阪神牝馬特別(OP)",
          "displayRace": "阪神牝馬特別",
          "distance": "芝2000",
          "grade": "jra_grade",
          "entry": "9",
          "result": "7",
          "favorite": "6"
        },
        {
          "date": {
            "year": 1982,
            "month": 11,
            "day": 21
          },
          "racecourse": "京都",
          "race": "エリザベス女王杯(OP)",
          "displayRace": "エリザベス女王杯",
          "distance": "芝2400",
          "grade": "jra_big10",
          "entry": "19",
          "result": "3",
          "favorite": "13"
        },
        {
          "date": {
            "year": 1982,
            "month": 10,
            "day": 31
          },
          "racecourse": "京都",
          "race": "京都牝馬特別(OP)",
          "displayRace": "京都牝馬特別",
          "distance": "芝1600",
          "grade": "jra_grade",
          "entry": "14",
          "result": "4",
          "favorite": "6"
        },
        {
          "date": {
            "year": 1982,
            "month": 8,
            "day": 8
          },
          "racecourse": "阪神",
          "race": "北九州記念(OP)",
          "displayRace": "北九州記念",
          "distance": "芝1600",
          "grade": "jra_grade",
          "entry": "10",
          "result": "10",
          "favorite": "2"
        },
        {
          "date": {
            "year": 1982,
            "month": 3,
            "day": 21
          },
          "racecourse": "阪神",
          "race": "阪神4歳牝馬特別(OP)",
          "displayRace": "阪神4歳牝馬特別",
          "distance": "芝1400",
          "grade": "jra_grade",
          "entry": "18",
          "result": "16",
          "favorite": "18"
        }
      ],
      "source": "python_scraping",
      "englishName": "Lovely Star",
      "prizeMoney": {
        "total": "3,667万円",
        "central": "3,667万円",
        "local": "0万円"
      },
      "damId": "good-sapphire"
    },
    {
      "id": "wonder-fang",
      "name": "ワンダーファング",
      "foaled": {
        "year": 1996,
        "month": 3,
        "day": 11
      },
      "sex": "male",
      "breed": "サラ",
      "sire": "フォティテン(US)",
      "dam": "ラブリースター",
      "color": "栗毛",
      "breeder": "信岡牧場（浦河町）",
      "netkeibaId": "1996100677",
      "raceStats": {
        "total": {
          "runs": 17,
          "wins": 4
        },
        "divisions": []
      },
      "raceResults": [
        {
          "date": {
            "year": 2000,
            "month": 9,
            "day": 16
          },
          "racecourse": "阪神",
          "race": "阪神ジャンプS(JGIII)",
          "displayRace": "阪神ジャンプS",
          "distance": "障3170",
          "grade": "jra_jg3",
          "entry": "9",
          "result": "5",
          "favorite": "2"
        },
        {
          "date": {
            "year": 2000,
            "month": 3,
            "day": 5
          },
          "racecourse": "中京",
          "race": "トヨタ賞中京記念(GIII)",
          "displayRace": "中京記念",
          "distance": "芝2000",
          "grade": "jra_g3",
          "entry": "14",
          "result": "11",
          "favorite": "12"
        },
        {
          "date": {
            "year": 2000,
            "month": 2,
            "day": 6
          },
          "racecourse": "小倉",
          "race": "小倉大賞典(GIII)",
          "displayRace": "小倉大賞典",
          "distance": "芝1800",
          "grade": "jra_g3",
          "entry": "16",
          "result": "13",
          "favorite": "8"
        },
        {
          "date": {
            "year": 2000,
            "month": 1,
            "day": 23
          },
          "racecourse": "中山",
          "race": "アメリカジョッキーC(GII)",
          "displayRace": "アメリカジョッキーC",
          "distance": "芝2200",
          "grade": "jra_g2",
          "entry": "14",
          "result": "9",
          "favorite": "7"
        },
        {
          "date": {
            "year": 1999,
            "month": 6,
            "day": 6
          },
          "racecourse": "東京",
          "race": "東京優駿(GI)",
          "displayRace": "東京優駿",
          "distance": "芝2400",
          "grade": "jra_g1",
          "entry": "18",
          "result": "9",
          "favorite": "13"
        },
        {
          "date": {
            "year": 1999,
            "month": 4,
            "day": 18
          },
          "racecourse": "中山",
          "race": "皐月賞(GI)",
          "displayRace": "皐月賞",
          "distance": "芝2000",
          "grade": "jra_g1",
          "entry": "17",
          "result": "除",
          "favorite": ""
        },
        {
          "date": {
            "year": 1999,
            "month": 3,
            "day": 21
          },
          "racecourse": "中山",
          "race": "フジTVスプリングS(GII)",
          "displayRace": "スプリングS",
          "distance": "芝1800",
          "grade": "jra_g2",
          "entry": "16",
          "result": "1",
          "favorite": "11"
        },
        {
          "date": {
            "year": 1999,
            "month": 2,
            "day": 28
          },
          "racecourse": "阪神",
          "race": "アーリントンC(GIII)",
          "displayRace": "アーリントンC",
          "distance": "芝1600",
          "grade": "jra_g3",
          "entry": "14",
          "result": "9",
          "favorite": "6"
        },
        {
          "date": {
            "year": 1998,
            "month": 12,
            "day": 26
          },
          "racecourse": "阪神",
          "race": "ラジオたんぱ杯3歳S(GIII)",
          "displayRace": "ラジオたんぱ杯3歳S",
          "distance": "芝2000",
          "grade": "jra_g3",
          "entry": "11",
          "result": "8",
          "favorite": "9"
        }
      ],
      "source": "python_scraping",
      "englishName": "Wonder Fang",
      "prizeMoney": {
        "total": "9,208万円",
        "central": "9,208万円",
        "local": "0万円"
      },
      "damId": "lovely-star"
    },
    {
      "id": "wonder-perfume",
      "name": "ワンダーパヒューム",
      "foaled": {
        "year": 1992,
        "month": 3,
        "day": 7
      },
      "sex": "female",
      "breed": "サラ",
      "sire": "フォティテン(US)",
      "dam": "ラブリースター",
      "color": "鹿毛",
      "breeder": "信岡牧場（浦河町）",
      "netkeibaId": "1992105710",
      "raceStats": {
        "total": {
          "runs": 9,
          "wins": 2
        },
        "divisions": []
      },
      "raceResults": [
        {
          "date": {
            "year": 1996,
            "month": 1,
            "day": 28
          },
          "racecourse": "京都",
          "race": "京都牝馬特別(GIII)",
          "displayRace": "京都牝馬特別",
          "distance": "芝1600",
          "grade": "jra_g3",
          "entry": "12",
          "result": "中",
          "favorite": "2"
        },
        {
          "date": {
            "year": 1995,
            "month": 12,
            "day": 17
          },
          "racecourse": "阪神",
          "race": "サンスポ阪神牝馬特別(GII)",
          "displayRace": "阪神牝馬特別",
          "distance": "芝2000",
          "grade": "jra_g2",
          "entry": "12",
          "result": "10",
          "favorite": "8"
        },
        {
          "date": {
            "year": 1995,
            "month": 11,
            "day": 12
          },
          "racecourse": "京都",
          "race": "エリザベス女王杯(GI)",
          "displayRace": "エリザベス女王杯",
          "distance": "芝2400",
          "grade": "jra_g1",
          "entry": "18",
          "result": "16",
          "favorite": "4"
        },
        {
          "date": {
            "year": 1995,
            "month": 10,
            "day": 22
          },
          "racecourse": "京都",
          "race": "関西TVローズS(GII)",
          "displayRace": "ローズS",
          "distance": "芝2000",
          "grade": "jra_g2",
          "entry": "16",
          "result": "4",
          "favorite": "3"
        },
        {
          "date": {
            "year": 1995,
            "month": 5,
            "day": 21
          },
          "racecourse": "東京",
          "race": "優駿牝馬(GI)",
          "displayRace": "優駿牝馬",
          "distance": "芝2400",
          "grade": "jra_g1",
          "entry": "18",
          "result": "3",
          "favorite": "7"
        },
        {
          "date": {
            "year": 1995,
            "month": 4,
            "day": 9
          },
          "racecourse": "京都",
          "race": "桜花賞(GI)",
          "displayRace": "桜花賞",
          "distance": "芝1600",
          "grade": "jra_g1",
          "entry": "18",
          "result": "1",
          "favorite": "7"
        }
      ],
      "source": "python_scraping",
      "englishName": "Wonder Perfume",
      "prizeMoney": {
        "total": "1億6,965万円",
        "central": "1億6,965万円",
        "local": "0万円"
      },
      "damId": "lovely-star"
    },
    {
      "id": "kuin-onwaado",
      "name": "クインオンワード",
      "foaled": {
        "year": 1957
      },
      "sex": "female",
      "breed": "サラ",
      "sire": "ヒンドスタン",
      "dam": "フレーミングフアイア",
      "color": "",
      "breeder": "",
      "netkeibaId": "1957z00281",
      "raceStats": {
        "total": {
          "runs": 13,
          "wins": 6
        },
        "divisions": []
      },
      "raceResults": [
        {
          "date": {
            "year": 1961,
            "month": 1,
            "day": 22
          },
          "racecourse": "京都",
          "race": "日本経済新春盃競走(OP)",
          "displayRace": "日本経済新春盃",
          "distance": "芝2400",
          "grade": "jra_grade",
          "entry": "9",
          "result": "1",
          "favorite": "3"
        },
        {
          "date": {
            "year": 1960,
            "month": 12,
            "day": 25
          },
          "racecourse": "阪神",
          "race": "朝日チャレンジC(OP)",
          "displayRace": "朝日チャレンジC",
          "distance": "芝2000",
          "grade": "jra_grade",
          "entry": "8",
          "result": "6",
          "favorite": "6"
        },
        {
          "date": {
            "year": 1960,
            "month": 12,
            "day": 11
          },
          "racecourse": "阪神",
          "race": "阪神牝馬特別競走(OP)",
          "displayRace": "阪神牝馬特別",
          "distance": "芝1800",
          "grade": "jra_grade",
          "entry": "10",
          "result": "1",
          "favorite": "1"
        },
        {
          "date": {
            "year": 1960,
            "month": 10,
            "day": 30
          },
          "racecourse": "阪神",
          "race": "阪神大賞典競走(OP)",
          "displayRace": "阪神大賞典",
          "distance": "芝2200",
          "grade": "jra_grade",
          "entry": "7",
          "result": "6",
          "favorite": "4"
        },
        {
          "date": {
            "year": 1960,
            "month": 10,
            "day": 16
          },
          "racecourse": "阪神",
          "race": "神戸盃競走(OP)",
          "displayRace": "神戸盃",
          "distance": "芝2000",
          "grade": "jra_grade",
          "entry": "5",
          "result": "1",
          "favorite": "5"
        },
        {
          "date": {
            "year": 1960,
            "month": 5,
            "day": 22
          },
          "racecourse": "東京",
          "race": "優駿牝馬競走(OP)",
          "displayRace": "優駿牝馬",
          "distance": "芝2400",
          "grade": "jra_big8",
          "entry": "26",
          "result": "2",
          "favorite": "4"
        },
        {
          "date": {
            "year": 1960,
            "month": 3,
            "day": 27
          },
          "racecourse": "阪神",
          "race": "桜花賞競走(OP)",
          "displayRace": "桜花賞",
          "distance": "芝1600",
          "grade": "jra_big8",
          "entry": "20",
          "result": "18",
          "favorite": "6"
        }
      ],
      "source": "python_scraping",
      "prizeMoney": {
        "total": "0万円"
      },
      "damId": "flaming-fire"
    },
    {
      "id": "top-run",
      "name": "トツプラン",
      "foaled": {
        "year": 1954
      },
      "sex": "male",
      "breed": "サラ",
      "sire": "Arctic Prince",
      "dam": "フレーミングフアイア",
      "color": "栗毛",
      "breeder": "浦河町",
      "netkeibaId": "000a00098d",
      "raceStats": {
        "total": {
          "runs": 26,
          "wins": 9
        },
        "divisions": []
      },
      "raceResults": [
        {
          "date": {
            "year": 1958,
            "month": 12,
            "day": 28
          },
          "racecourse": "阪神",
          "race": "朝日チヤレンジC(OP)",
          "displayRace": "朝日チャレンジC",
          "distance": "芝2000",
          "grade": "jra_grade",
          "entry": "10",
          "result": "5",
          "favorite": "3"
        },
        {
          "date": {
            "year": 1958,
            "month": 11,
            "day": 30
          },
          "racecourse": "京都",
          "race": "京都記念競走(OP)",
          "displayRace": "京都記念(秋)",
          "distance": "芝2200",
          "grade": "jra_grade",
          "entry": "7",
          "result": "4",
          "favorite": "3"
        },
        {
          "date": {
            "year": 1958,
            "month": 6,
            "day": 29
          },
          "racecourse": "阪神",
          "race": "宝塚盃競走(OP)",
          "displayRace": "宝塚盃",
          "distance": "芝2200",
          "grade": "jra_grade",
          "entry": "8",
          "result": "7",
          "favorite": "1"
        },
        {
          "date": {
            "year": 1958,
            "month": 4,
            "day": 29
          },
          "racecourse": "京都",
          "race": "天皇賞競走(OP)",
          "displayRace": "天皇賞(春)",
          "distance": "芝3200",
          "grade": "jra_big8",
          "entry": "12",
          "result": "4",
          "favorite": "1"
        },
        {
          "date": {
            "year": 1958,
            "month": 1,
            "day": 19
          },
          "racecourse": "京都",
          "race": "日本経済新春盃競走(OP)",
          "displayRace": "日本経済新春盃",
          "distance": "芝2400",
          "grade": "jra_grade",
          "entry": "9",
          "result": "1",
          "favorite": "1"
        },
        {
          "date": {
            "year": 1957,
            "month": 11,
            "day": 17
          },
          "racecourse": "京都",
          "race": "菊花賞競走(OP)",
          "displayRace": "菊花賞",
          "distance": "芝3000",
          "grade": "jra_big8",
          "entry": "15",
          "result": "4",
          "favorite": "4"
        },
        {
          "date": {
            "year": 1957,
            "month": 11,
            "day": 3
          },
          "racecourse": "阪神",
          "race": "阪神大賞典競走(OP)",
          "displayRace": "阪神大賞典",
          "distance": "芝2200",
          "grade": "jra_grade",
          "entry": "10",
          "result": "1",
          "favorite": "5"
        },
        {
          "date": {
            "year": 1957,
            "month": 10,
            "day": 6
          },
          "racecourse": "京都",
          "race": "京都特別競走(OP)",
          "displayRace": "京都特別",
          "distance": "芝2200",
          "grade": "jra_grade",
          "entry": "11",
          "result": "2",
          "favorite": "4"
        },
        {
          "date": {
            "year": 1957,
            "month": 5,
            "day": 26
          },
          "racecourse": "東京",
          "race": "東京優駿競走(OP)",
          "displayRace": "東京優駿",
          "distance": "芝2400",
          "grade": "jra_big8",
          "entry": "20",
          "result": "19",
          "favorite": "4"
        },
        {
          "date": {
            "year": 1957,
            "month": 4,
            "day": 21
          },
          "racecourse": "中山",
          "race": "皐月賞競走(OP)",
          "displayRace": "皐月賞",
          "distance": "芝2000",
          "grade": "jra_big8",
          "entry": "14",
          "result": "3",
          "favorite": "6"
        }
      ],
      "source": "python_scraping",
      "englishName": "Top Run",
      "prizeMoney": {
        "total": "0万円"
      },
      "damId": "flaming-fire"
    }
  ]
}
