{
  "metadata": {
    "pedigreeName": "ガルカ",
    "rootHorseId": "galka",
    "lastUpdated": "2025-10-04T17:35:00.000Z",
    "source": "attribute_mapping_reverted",
    "isTraditionalFamily": true
  },
  "horses": [
    {
      "id": "galka",
      "name": "ガルカ",
      "foaled": {
        "year": 1898
      },
      "importedYear": "1900",
      "sex": "female",
      "breed": "オロ",
      "sire": "グラズンチツク",
      "dam": "フアチマ",
      "color": "鹿毛",
      "breeder": "露",
      "owner": "下総御料牧場",
      "netkeibaId": "000a018aa6",
      "source": "python_scraping, 『馬牛明細調 下総御料牧場 明治36年5月20日現在』10/42コマ, 『中央獣医会雑誌 14(7)』pp.1-9, 『アラブ・アングロアラブ・準サラブレッド血統書 第1巻』p.896, 『日本馬政史 続 第2』p.21, 『日本之産馬 1(5)』p.40",
      "comment": "オルローフロストプチン種。ロシア・ガラホウ牧場産。ワローネシユ市で1100ルーブルで購入。母はnetkeiba, 『アラブ血統書』では「フアチス」だが、『馬牛明細調』『馬匹血統登録書』『アラブ血統書』（第七ガルカの項）では「フアチマ」。「フアチマ」を採用。輸入年は『日本馬政史 続 第2』では1900年, 『日本におけるアングロアラブの母系系統』p.38では1901年。『日本之産馬 1(5)』p.40にはオロ種について「明治三十三年に一回輸入されたる」の記述有。1900年輸入を採用。綴りは不明だが、女性名の愛称「Галка(Galka)」か。"
    },
    {
      "id": "dai7-galka",
      "name": "第七ガルカ",
      "foaled": {
        "year": 1917,
        "month": 4,
        "day": 13
      },
      "sex": "female",
      "breed": "アア",
      "sire": "サツパーダンス",
      "dam": "ガルカ",
      "color": "鹿毛",
      "breeder": "下総御料牧場",
      "netkeibaId": "000a018aa7",
      "raceStats": {
        "total": {
          "runs": 0,
          "wins": 0
        },
        "divisions": []
      },
      "raceResults": [],
      "source": "python_scraping, 『アラブ・アングロアラブ・準サラブレッド血統書 第1巻』p.896",
      "prizeMoney": {
        "total": "0万円"
      },
      "damId": "galka",
      "furigana": "ダイナナガルカ"
    },
    {
      "id": "kumokoma",
      "pedigreeName": "雲駒",
      "name": "クモコマ",
      "foaled": {
        "year": 1922,
        "month": 5,
        "day": 12
      },
      "sex": "female",
      "breed": "準サラ",
      "sire": "ハアリー",
      "dam": "第七ガルカ",
      "color": "鹿毛",
      "breeder": "下総御料牧場",
      "netkeibaId": "000a00b700",
      "raceStats": {
        "total": {
          "runs": null,
          "wins": 1
        },
        "divisions": []
      },
      "raceResults": [],
      "source": "python_scraping, 『アラブ・アングロアラブ・準サラブレッド血統書 第1巻』p.1142, 『競馬成績書 昭和5年 秋季』p.117, 『競馬成績書 昭和6年春季』p.318",
      "prizeMoney": {
        "total": null
      },
      "damId": "dai7-galka",
      "furigana": "クモコマ"
    },
    {
      "id": "sutaakappu",
      "name": "スターカップ",
      "foaled": {
        "year": 1935,
        "month": 6,
        "day": 8
      },
      "sex": "female",
      "breed": "準サラ",
      "sire": "バラツケー(FR)",
      "dam": "雲駒",
      "color": "鹿毛",
      "breeder": "浜本幸三郎（北海道沙流郡門別町）",
      "netkeibaId": "000a00ba05",
      "registration": "本登録番号12号",
      "raceStats": {
        "total": {
          "runs": null,
          "wins": null
        },
        "divisions": []
      },
      "raceResults": [],
      "source": "python_scraping, 『アラブ・アングロアラブ・準サラブレッド血統書 第1巻』p.731",
      "prizeMoney": {
        "total": null
      },
      "damId": "kumokoma"
    },
    {
      "id": "takatsubaki-1952",
      "name": "タカツバキ",
      "foaled": {
        "year": 1952
      },
      "sex": "female",
      "breed": "アア",
      "sire": "ラツキーパーク",
      "dam": "スターカップ",
      "color": "",
      "breeder": "浦河町",
      "netkeibaId": "000a00cb78",
      "raceStats": {
        "total": {
          "runs": 0,
          "wins": 0
        },
        "divisions": []
      },
      "raceResults": [],
      "source": "python_scraping",
      "englishName": "Takatsubaki",
      "prizeMoney": {
        "total": "0万円"
      },
      "damId": "sutaakappu",
      "linkName": "タカツバキ(1952)"
    },
    {
      "id": "misukatsupu",
      "name": "ミスカツプ",
      "foaled": {
        "year": 1960
      },
      "sex": "female",
      "breed": "アア",
      "sire": "セイユウ",
      "dam": "タカツバキ",
      "color": "黒鹿毛",
      "breeder": "",
      "netkeibaId": "000a00d21a",
      "raceStats": {
        "total": {
          "runs": 38,
          "wins": 27
        },
        "divisions": []
      },
      "raceResults": [
        {
          "date": {
            "year": 1964,
            "month": 5,
            "day": 5
          },
          "racecourse": "京都",
          "race": "タマツバキ記念(OP)",
          "displayRace": "タマツバキ記念(春)",
          "distance": "芝2000",
          "grade": "jra_grade",
          "entry": "12",
          "result": "1",
          "favorite": "4"
        },
        {
          "date": {
            "year": 1964,
            "month": 3,
            "day": 8
          },
          "racecourse": "中京",
          "race": "アラブ大賞典(OP)",
          "displayRace": "アラブ大賞典",
          "distance": "芝1800",
          "grade": "jra_grade",
          "entry": "6",
          "result": "6",
          "favorite": "1"
        },
        {
          "date": {
            "year": 1963,
            "month": 6,
            "day": 30
          },
          "racecourse": "阪神",
          "race": "宝塚記念競走(OP)",
          "displayRace": "宝塚記念",
          "distance": "芝2000",
          "grade": "jra_grade",
          "entry": "10",
          "result": "9",
          "favorite": "5"
        },
        {
          "date": {
            "year": 1963,
            "month": 4,
            "day": 21
          },
          "racecourse": "京都",
          "race": "タマツバキ記念競走(OP)",
          "displayRace": "タマツバキ記念(春)",
          "distance": "芝2000",
          "grade": "jra_grade",
          "entry": "8",
          "result": "1",
          "favorite": "1"
        },
        {
          "date": {
            "year": 1963,
            "month": 3,
            "day": 3
          },
          "racecourse": "中京",
          "race": "アラブ大賞典競走(OP)",
          "displayRace": "アラブ大賞典",
          "distance": "芝1800",
          "grade": "jra_grade",
          "entry": "8",
          "result": "1",
          "favorite": "1"
        }
      ],
      "source": "python_scraping",
      "prizeMoney": {
        "total": "0万円"
      },
      "damId": "takatsubaki-1952"
    },
    {
      "id": "taihei",
      "name": "タイヘイ",
      "foaled": {
        "year": 1955
      },
      "sex": "male",
      "breed": "アア",
      "sire": "ニユーバラツケー",
      "dam": "カツプフオード",
      "color": "鹿毛",
      "breeder": "",
      "netkeibaId": "000a00c366",
      "raceStats": {
        "total": {
          "runs": 55,
          "wins": 17
        },
        "divisions": []
      },
      "raceResults": [
        {
          "date": {
            "year": 1959,
            "month": 5,
            "day": 10
          },
          "racecourse": "京都",
          "race": "タマツバキ記念競走(OP)",
          "displayRace": "タマツバキ記念(春)",
          "distance": "芝2000",
          "grade": "jra_grade",
          "entry": "12",
          "result": "2",
          "favorite": "2"
        }
      ],
      "source": "python_scraping",
      "englishName": "Taihei",
      "prizeMoney": {
        "total": "0万円"
      },
      "damId": "katsupufuoodo"
    },
    {
      "id": "katsupufuoodo",
      "name": "カツプフオード",
      "foaled": {
        "year": 1945
      },
      "sex": "female",
      "breed": "アア",
      "sire": "方景",
      "dam": "スターカップ",
      "color": "鹿毛",
      "breeder": "",
      "netkeibaId": "000a00c950",
      "raceStats": {
        "total": {
          "runs": 0,
          "wins": 0
        },
        "divisions": []
      },
      "raceResults": [],
      "source": "python_scraping",
      "prizeMoney": {
        "total": "0万円"
      },
      "damId": "sutaakappu"
    }
  ]
}
