{
  "metadata": {
    "pedigreeName": "Jeune Amour",
    "rootHorseId": "jeune-amour",
    "lastUpdated": "2025-09-27T15:10:17.795968Z",
    "source": "python_scraping"
  },
  "horses": [
    {
      "id": "jeune-amour",
      "name": "ジユーヌアムール",
      "foaled": "{'year': 1962}",
      "foaledArray": ["1962"],
      "sex": "female",
      "breed": "サラブレッド種",
      "sire": "Sica Boy(FR)",
      "dam": "Dark Caprice",
      "color": "栗毛",
      "breeder": "英",
      "netkeibaId": "000a0037bc",
      "raceStats": {
        "total": {
          "runs": 0,
          "wins": 0
        },
        "divisions": []
      },
      "raceResults": [],
      "source": "python_scraping",
      "englishName": "Jeune Amour"
    },
    {
      "id": "open-cherry",
      "name": "オープンチェリー",
      "foaled": "{'year': 1969}",
      "foaledArray": ["1969"],
      "sex": "female",
      "breed": "サラブレッド種",
      "sire": "ハードリドン(GB)",
      "dam": "ジユーヌアムール",
      "color": "鹿毛",
      "breeder": "浦河町",
      "netkeibaId": "1955102104",
      "raceStats": {
        "total": {
          "runs": 5,
          "wins": 1
        },
        "divisions": []
      },
      "raceResults": [],
      "source": "python_scraping",
      "englishName": "Open Cherry",
      "prizeMoney": {
        "total": "0万円"
      },
      "damId": "jeune-amour"
    },
    {
      "id": "yusho-swallow",
      "name": "ユーショウスワロー",
      "foaled": "{'year': 1982, 'month': 5, 'day': 9}",
      "foaledArray": ["1982", "05", "09"],
      "sex": "female",
      "breed": "サラブレッド種",
      "sire": "マイスワロー(GB)",
      "dam": "オープンチェリー",
      "color": "黒鹿毛",
      "breeder": "川越牧場（浦河町）",
      "netkeibaId": "1982102786",
      "raceStats": {
        "total": {
          "runs": 7,
          "wins": 3
        },
        "divisions": []
      },
      "raceResults": [
        {
          "date": {
            "year": 1984,
            "month": 9,
            "day": 2
          },
          "racecourse": "小倉",
          "race": "小倉3歳S(OP)",
          "displayRace": "小倉3歳S",
          "distance": "芝1200",
          "grade": "jra_g3",
          "entry": "11",
          "result": "2",
          "favorite": "2"
        }
      ],
      "source": "python_scraping",
      "englishName": "Yusho Swallow",
      "prizeMoney": {
        "total": "0万円"
      },
      "damId": "open-cherry"
    }
  ]
}
