{
  "metadata": {
    "pedigreeName": "Maia",
    "rootHorseId": "maia",
    "lastUpdated": "2025-09-22T15:54:16.197468Z",
    "source": "python_scraping_updated"
  },
  "horses": [
    {
      "id": "maia",
      "name": "マイア",
      "foaled": "{'year': 1972}",
      "foaledArray": ["1972"],
      "sex": "female",
      "breed": "サラブレッド種",
      "sire": "Cipol",
      "dam": "Leandra",
      "dam_netkeiba_id": "",
      "color": "鹿毛",
      "breeder": "亜",
      "netkeibaId": "000a0060dd",
      "raceStats": {
        "total": {
          "runs": 0,
          "wins": 0
        },
        "divisions": []
      },
      "raceResults": [],
      "source": "python_scraping",
      "englishName": "Maia"
    },
    {
      "id": "northern-maia",
      "name": "ノーザンマイア",
      "foaled": "{'year': 1990, 'month': 3, 'day': 6}",
      "foaledArray": ["1990", "03", "06"],
      "sex": "female",
      "breed": "サラブレッド種",
      "sire": "ノーザンテースト(CAN)",
      "dam": "マイア",
      "dam_netkeiba_id": "000a0060dd",
      "color": "鹿毛",
      "breeder": "社台ファーム（早来町）",
      "netkeibaId": "1990104643",
      "raceStats": {
        "total": {
          "runs": 48,
          "wins": 4
        },
        "divisions": []
      },
      "raceResults": [
        {
          "date": {
            "year": 1993,
            "month": 5,
            "day": 2
          },
          "racecourse": "東京",
          "race": "サンスポ4歳牝馬特別(GII)",
          "displayRace": "4歳牝馬特別（東）",
          "distance": "芝2000",
          "grade": "jra_g2",
          "entry": "14",
          "result": "12",
          "favorite": "10"
        }
      ],
      "source": "python_scraping",
      "englishName": "Northern Maia",
      "prizeMoney": {
        "total": "7,522万円",
        "central": "7,522万円",
        "local": "0万円"
      },
      "damId": "maia"
    },
    {
      "id": "katsura-driver",
      "name": "カツラドライバー",
      "foaled": "{'year': 1998, 'month': 3, 'day': 9}",
      "foaledArray": ["1998", "03", "09"],
      "sex": "female",
      "breed": "サラブレッド種",
      "sire": "ニホンピロウイナー",
      "dam": "ノーザンマイア",
      "dam_netkeiba_id": "1990104643",
      "color": "鹿毛",
      "breeder": "ノーザンファーム（早来町）",
      "netkeibaId": "1998101801",
      "raceStats": {
        "total": {
          "runs": 4,
          "wins": 0
        },
        "divisions": []
      },
      "raceResults": [],
      "source": "python_scraping",
      "englishName": "Katsura Driver",
      "prizeMoney": {
        "total": "130万円",
        "central": "130万円",
        "local": "0万円"
      },
      "damId": "northern-maia"
    },
    {
      "id": "admire-morale",
      "name": "アドマイヤモラール",
      "foaled": "{'year': 2013, 'month': 2, 'day': 9}",
      "foaledArray": ["2013", "02", "09"],
      "sex": "male",
      "breed": "サラブレッド種",
      "sire": "キンシャサノキセキ",
      "dam": "カツラドライバー",
      "dam_netkeiba_id": "1998101801",
      "color": "黒鹿毛",
      "breeder": "ノーザンファーム（安平町）",
      "netkeibaId": "2013105825",
      "raceStats": {
        "total": {
          "runs": 10,
          "wins": 1
        },
        "divisions": []
      },
      "raceResults": [
        {
          "date": {
            "year": 2016,
            "month": 4,
            "day": 17
          },
          "racecourse": "中山",
          "race": "皐月賞(GI)",
          "displayRace": "皐月賞",
          "distance": "芝2000",
          "grade": "jra_g1",
          "entry": "18",
          "result": "18",
          "favorite": "17"
        },
        {
          "date": {
            "year": 2016,
            "month": 3,
            "day": 20
          },
          "racecourse": "中山",
          "race": "フジTVスプリングS(GII)",
          "displayRace": "スプリングS",
          "distance": "芝1800",
          "grade": "jra_g2",
          "entry": "11",
          "result": "11",
          "favorite": "7"
        },
        {
          "date": {
            "year": 2016,
            "month": 1,
            "day": 17
          },
          "racecourse": "中山",
          "race": "京成杯(GIII)",
          "displayRace": "京成杯",
          "distance": "芝2000",
          "grade": "jra_g3",
          "entry": "15",
          "result": "4",
          "favorite": "10"
        },
        {
          "date": {
            "year": 2015,
            "month": 12,
            "day": 20
          },
          "racecourse": "阪神",
          "race": "朝日フューチュリティ(GI)",
          "displayRace": "朝日杯フューチュリティS",
          "distance": "芝1600",
          "grade": "jra_g1",
          "entry": "16",
          "result": "8",
          "favorite": "9"
        },
        {
          "date": {
            "year": 2015,
            "month": 11,
            "day": 7
          },
          "racecourse": "東京",
          "race": "京王杯2歳S(GII)",
          "displayRace": "京王杯2歳S",
          "distance": "芝1400",
          "grade": "jra_g2",
          "entry": "18",
          "result": "2",
          "favorite": "6"
        }
      ],
      "source": "python_scraping",
      "englishName": "Admire Morale",
      "prizeMoney": {
        "total": "2,868万円",
        "central": "2,868万円",
        "local": "0万円"
      },
      "damId": "katsura-driver"
    },
    {
      "id": "f-t-maia",
      "name": "エフティマイア",
      "foaled": "{'year': 2005, 'month': 2, 'day': 14}",
      "foaledArray": ["2005", "02", "14"],
      "sex": "female",
      "breed": "サラブレッド種",
      "sire": "フジキセキ",
      "dam": "カツラドライバー",
      "color": "鹿毛",
      "breeder": "ノーザンファーム（早来町）",
      "netkeibaId": "2005102499",
      "raceStats": {
        "total": {
          "runs": 19,
          "wins": 3
        },
        "divisions": []
      },
      "raceResults": [
        {
          "date": {
            "year": 2010,
            "month": 8,
            "day": 8
          },
          "racecourse": "新潟",
          "race": "関屋記念(GIII)",
          "displayRace": "関屋記念",
          "distance": "芝1600",
          "grade": "jra_g3",
          "entry": "18",
          "result": "14",
          "favorite": "11"
        },
        {
          "date": {
            "year": 2009,
            "month": 11,
            "day": 8
          },
          "racecourse": "東京",
          "race": "アルゼンチン共和国杯(GII)",
          "displayRace": "アルゼンチン共和国杯",
          "distance": "芝2500",
          "grade": "jra_g2",
          "entry": "18",
          "result": "16",
          "favorite": "18"
        },
        {
          "date": {
            "year": 2009,
            "month": 10,
            "day": 18
          },
          "racecourse": "東京",
          "race": "府中牝馬S(GIII)",
          "displayRace": "府中牝馬S",
          "distance": "芝1800",
          "grade": "jra_g3",
          "entry": "18",
          "result": "13",
          "favorite": "8"
        },
        {
          "date": {
            "year": 2009,
            "month": 9,
            "day": 13
          },
          "racecourse": "中山",
          "race": "京成杯オータムH(GIII)",
          "displayRace": "京成杯オータムH",
          "distance": "芝1600",
          "grade": "jra_g3",
          "entry": "16",
          "result": "11",
          "favorite": "5"
        },
        {
          "date": {
            "year": 2008,
            "month": 11,
            "day": 16
          },
          "racecourse": "京都",
          "race": "エリザベス女王杯(GI)",
          "displayRace": "エリザベス女王杯",
          "distance": "芝2200",
          "grade": "jra_g1",
          "entry": "18",
          "result": "13",
          "favorite": "6"
        },
        {
          "date": {
            "year": 2008,
            "month": 10,
            "day": 19
          },
          "racecourse": "京都",
          "race": "秋華賞(GI)",
          "displayRace": "秋華賞",
          "distance": "芝2000",
          "grade": "jra_g1",
          "entry": "18",
          "result": "5",
          "favorite": "3"
        },
        {
          "date": {
            "year": 2008,
            "month": 8,
            "day": 17
          },
          "racecourse": "札幌",
          "race": "クイーンS(GIII)",
          "displayRace": "クイーンS",
          "distance": "芝1800",
          "grade": "jra_g3",
          "entry": "13",
          "result": "5",
          "favorite": "3"
        },
        {
          "date": {
            "year": 2008,
            "month": 5,
            "day": 25
          },
          "racecourse": "東京",
          "race": "優駿牝馬(GI)",
          "displayRace": "優駿牝馬",
          "distance": "芝2400",
          "grade": "jra_g1",
          "entry": "18",
          "result": "2",
          "favorite": "13"
        },
        {
          "date": {
            "year": 2008,
            "month": 4,
            "day": 13
          },
          "racecourse": "阪神",
          "race": "桜花賞(GI)",
          "displayRace": "桜花賞",
          "distance": "芝1600",
          "grade": "jra_g1",
          "entry": "17",
          "result": "2",
          "favorite": "15"
        },
        {
          "date": {
            "year": 2008,
            "month": 2,
            "day": 23
          },
          "racecourse": "東京",
          "race": "デイリー杯クイーンC(GIII)",
          "displayRace": "クイーンC",
          "distance": "芝1600",
          "grade": "jra_g3",
          "entry": "16",
          "result": "6",
          "favorite": "10"
        },
        {
          "date": {
            "year": 2007,
            "month": 12,
            "day": 16
          },
          "racecourse": "中山",
          "race": "フェアリーS(GIII)",
          "displayRace": "フェアリーS",
          "distance": "芝1200",
          "grade": "jra_g3",
          "entry": "16",
          "result": "5",
          "favorite": "7"
        },
        {
          "date": {
            "year": 2007,
            "month": 12,
            "day": 2
          },
          "racecourse": "阪神",
          "race": "阪神ジュベナイルF(GI)",
          "displayRace": "阪神ジュベナイルF",
          "distance": "芝1600",
          "grade": "jra_g1",
          "entry": "18",
          "result": "17",
          "favorite": "9"
        },
        {
          "date": {
            "year": 2007,
            "month": 11,
            "day": 10
          },
          "racecourse": "東京",
          "race": "京王杯2歳S(GII)",
          "displayRace": "京王杯2歳S",
          "distance": "芝1400",
          "grade": "jra_g2",
          "entry": "15",
          "result": "13",
          "favorite": "2"
        },
        {
          "date": {
            "year": 2007,
            "month": 9,
            "day": 2
          },
          "racecourse": "新潟",
          "race": "新潟2歳S(GIII)",
          "displayRace": "新潟2歳S",
          "distance": "芝1600",
          "grade": "jra_g3",
          "entry": "18",
          "result": "1",
          "favorite": "4"
        }
      ],
      "source": "python_scraping",
      "englishName": "F T Maia",
      "prizeMoney": {
        "total": "1億7,087万円",
        "central": "1億7,087万円",
        "local": "0万円"
      },
      "damId": "katsura-driver"
    }
  ]
}
