{
  "metadata": {
    "pedigreeName": "Manyara",
    "rootHorseId": "manyara",
    "lastUpdated": "2025-10-04T17:35:00.000Z",
    "source": "attribute_mapping_reverted"
  },
  "horses": [
    {
      "id": "manyara",
      "name": "マニヤラ",
      "foaled": {
        "year": 2011
      },
      "sex": "female",
      "breed": "サラブレッド種",
      "sire": "Manduro(GER)",
      "dam": "Genovefa",
      "color": "鹿毛",
      "breeder": "英",
      "netkeibaId": "000a014479",
      "raceStats": {
        "total": {
          "runs": 0,
          "wins": 0
        },
        "divisions": []
      },
      "raceResults": [],
      "source": "python_scraping",
      "englishName": "Manyara"
    },
    {
      "id": "ballerina",
      "name": "バレリーナ",
      "foaled": {
        "year": 2020,
        "month": 3,
        "day": 18
      },
      "sex": "female",
      "breed": "サラブレッド種",
      "sire": "ダイワメジャー",
      "dam": "マニヤラ",
      "color": "栗毛",
      "breeder": "服部牧場（新ひだか町）",
      "netkeibaId": "2020104674",
      "raceStats": {
        "total": {
          "runs": 9,
          "wins": 1
        },
        "divisions": []
      },
      "raceResults": [
        {
          "date": {
            "year": 2022,
            "month": 11,
            "day": 5
          },
          "racecourse": "阪神",
          "race": "KBSファンタジーS(GIII)",
          "displayRace": "ファンタジーS",
          "distance": "芝1400",
          "grade": "jra_g3",
          "entry": "12",
          "result": "9",
          "favorite": "3"
        },
        {
          "date": {
            "year": 2022,
            "month": 9,
            "day": 4
          },
          "racecourse": "小倉",
          "race": "小倉2歳S(GIII)",
          "displayRace": "小倉2歳S",
          "distance": "芝1200",
          "grade": "jra_g3",
          "entry": "13",
          "result": "2",
          "favorite": "9"
        }
      ],
      "source": "python_scraping",
      "englishName": "Ballerina",
      "prizeMoney": {
        "total": "2,027万円",
        "central": "2,027万円",
        "local": "0万円"
      },
      "damId": "manyara"
    }
  ]
}
