{
  "metadata": {
    "pedigreeName": "Rabbit Run",
    "rootHorseId": "rabbit-run",
    "lastUpdated": "2025-09-18T19:55:44.070447Z",
    "source": "python_scraping"
  },
  "horses": [
    {
      "id": "rabbit-run",
      "name": "ラビットラン",
      "foaled": "{'year': 2014, 'month': 3, 'day': 18}",
      "foaledArray": ["2014", "03", "18"],
      "sex": "female",
      "breed": "サラブレッド種",
      "sire": "Tapit(US)",
      "dam": "Amelia",
      "color": "栗毛",
      "breeder": "Alexander Groves Matz LLC（米）",
      "netkeibaId": "2014110010",
      "raceStats": {
        "total": {
          "runs": 0,
          "wins": 0
        },
        "divisions": []
      },
      "raceResults": [],
      "source": "python_scraping",
      "englishName": "Rabbit Run"
    }
  ]
}
